lottostar_cli/__init__.py
lottostar_cli/main.py
lottostar_cli/app/__init__.py
lottostar_cli/app/ballsets/__init__.py
lottostar_cli/app/ballsets/main.py
lottostar_cli/app/celery/__init__.py
lottostar_cli/app/celery/celery_launcher.py
lottostar_cli/app/cli/__init__.py
lottostar_cli/app/cli/main.py
lottostar_cli/app/config/__init__.py
lottostar_cli/app/config/main.py
lottostar_cli/app/file_processor/__init__.py
lottostar_cli/app/file_processor/csv_processor.py
lottostar_cli/app/file_processor/file_locator.py
lottostar_cli/app/tests/__init__.py
lottostar_cli/app/tests/test_cases.py
lottostar_cli/app/tickets/__init__.py
lottostar_cli/app/tickets/main.py
lottostar-0.1.7.dist-info/METADATA
lottostar-0.1.7.dist-info/WHEEL
lottostar-0.1.7.dist-info/entry_points.txt
lottostar-0.1.7.dist-info/top_level.txt
lottostar-0.1.7.dist-info/RECORD
