Metadata-Version: 2.1
Name: lottostar
Version: 0.1.7
Requires-Dist: click
Requires-Dist: celery
Requires-Dist: redis
